cliqestimsp/__init__.py
cliqestimsp/networkcli.cpython-311-darwin.so
cliqestimspp-0.1.1.dist-info/LICENSE.txt
cliqestimspp-0.1.1.dist-info/METADATA
cliqestimspp-0.1.1.dist-info/WHEEL
cliqestimspp-0.1.1.dist-info/top_level.txt
cliqestimspp-0.1.1.dist-info/RECORD
